JingtongPythonOpencv4ChuyiFix1/README.md
JingtongPythonOpencv4ChuyiFix1/__init__.py
JingtongPythonOpencv4ChuyiFix1/__main__.py
JingtongPythonOpencv4ChuyiFix1/file.epub
JingtongPythonOpencv4ChuyiFix1/index.html
JingtongPythonOpencv4ChuyiFix1/css/__init__.py
JingtongPythonOpencv4ChuyiFix1/css/annotations.css
JingtongPythonOpencv4ChuyiFix1/css/main.css
JingtongPythonOpencv4ChuyiFix1/css/normalize.css
JingtongPythonOpencv4ChuyiFix1/css/popup.css
JingtongPythonOpencv4ChuyiFix1/font/__init__.py
JingtongPythonOpencv4ChuyiFix1/font/fontello.eot
JingtongPythonOpencv4ChuyiFix1/font/fontello.svg
JingtongPythonOpencv4ChuyiFix1/font/fontello.ttf
JingtongPythonOpencv4ChuyiFix1/font/fontello.woff
JingtongPythonOpencv4ChuyiFix1/img/__init__.py
JingtongPythonOpencv4ChuyiFix1/img/annotator-glyph-sprite.png
JingtongPythonOpencv4ChuyiFix1/img/annotator-icon-sprite.png
JingtongPythonOpencv4ChuyiFix1/img/apple-touch-icon.png
JingtongPythonOpencv4ChuyiFix1/img/cancelfullscreen.png
JingtongPythonOpencv4ChuyiFix1/img/close.png
JingtongPythonOpencv4ChuyiFix1/img/fullscreen.png
JingtongPythonOpencv4ChuyiFix1/img/loader.gif
JingtongPythonOpencv4ChuyiFix1/img/menu-icon.png
JingtongPythonOpencv4ChuyiFix1/img/save.png
JingtongPythonOpencv4ChuyiFix1/img/saved.png
JingtongPythonOpencv4ChuyiFix1/img/settings-s.png
JingtongPythonOpencv4ChuyiFix1/img/settings.png
JingtongPythonOpencv4ChuyiFix1/img/star.png
JingtongPythonOpencv4ChuyiFix1/js/__init__.py
JingtongPythonOpencv4ChuyiFix1/js/epub.js
JingtongPythonOpencv4ChuyiFix1/js/epub.min.js
JingtongPythonOpencv4ChuyiFix1/js/epub.min.map
JingtongPythonOpencv4ChuyiFix1/js/hooks.min.js
JingtongPythonOpencv4ChuyiFix1/js/hooks.min.map
JingtongPythonOpencv4ChuyiFix1/js/reader.js
JingtongPythonOpencv4ChuyiFix1/js/reader.js.map
JingtongPythonOpencv4ChuyiFix1/js/reader.min.js
JingtongPythonOpencv4ChuyiFix1/js/reader.min.map
JingtongPythonOpencv4ChuyiFix1/js/hooks/__init__.py
JingtongPythonOpencv4ChuyiFix1/js/hooks/extensions/__init__.py
jingtong_python_opencv4_chuyi_fix1-2025.3.25.1.dist-info/METADATA
jingtong_python_opencv4_chuyi_fix1-2025.3.25.1.dist-info/WHEEL
jingtong_python_opencv4_chuyi_fix1-2025.3.25.1.dist-info/entry_points.txt
jingtong_python_opencv4_chuyi_fix1-2025.3.25.1.dist-info/top_level.txt
jingtong_python_opencv4_chuyi_fix1-2025.3.25.1.dist-info/RECORD
